flask_framework/__init__.py
flask_framework/app.py
flask_framework/azure.py
flask_framework/cli.py
flask_framework/server.py
flask_framework/wsgi.py
flask_framework/Config/__init__.py
flask_framework/Config/_exceptions.py
flask_framework/Config/config.py
flask_framework/Config/json.py
flask_framework/Config/yaml.py
flask_framework/Controllers/__init__.py
flask_framework/Controllers/WS/__init__.py
flask_framework/Controllers/Web/HTTP40XController.py
flask_framework/Controllers/Web/HTTP50XController.py
flask_framework/Controllers/Web/__init__.py
flask_framework/Database/__init__.py
flask_framework/Database/decorators.py
flask_framework/Database/driver.py
flask_framework/Database/migration.py
flask_framework/Deprecation/__init__.py
flask_framework/Exceptions/ConfigExceptions.py
flask_framework/Exceptions/QueryExceptions.py
flask_framework/Exceptions/RuntimeExceptions.py
flask_framework/Exceptions/__init__.py
flask_framework/Extensions/__init__.py
flask_framework/Extensions/loader.py
flask_framework/Libs/__init__.py
flask_framework/Libs/decorator.py
flask_framework/Server/ErrorHandler.py
flask_framework/Server/Middleware.py
flask_framework/Server/Plugins.py
flask_framework/Server/RequestHandler.py
flask_framework/Server/Socket.py
flask_framework/Server/WS.py
flask_framework/Server/Web.py
flask_framework/Server/__init__.py
flask_framework/Task/__init__.py
flask_framework/Utils/__init__.py
flask_framework/Utils/module.py
flask_framework/Utils/templates.py
flask_framework/Utils/utils.py
flask_framework/Utils/Auth/__init__.py
flask_framework/Utils/Auth/decorators.py
flask_framework/Utils/Auth/ldap.py
flask_framework/Utils/Auth/user.py
flask_framework/static/favicon.ico
flask_framework/static/css/app.css
flask_framework/static/css/app.csse
flask_framework/static/css/style.css
flask_framework/template/404.html
flask_framework/template/40x.html
flask_framework/template/500.html
flask_framework/template/50x.html
flask_framework/template/welcome.html
flask_framework_mvc-1.1.14.dist-info/licenses/LICENSE
flask_framework_mvc-1.1.14.dist-info/METADATA
flask_framework_mvc-1.1.14.dist-info/WHEEL
flask_framework_mvc-1.1.14.dist-info/entry_points.txt
flask_framework_mvc-1.1.14.dist-info/top_level.txt
flask_framework_mvc-1.1.14.dist-info/RECORD
