Metadata-Version: 2.4
Name: flask-framework-mvc
Version: 1.1.14
Summary: Flask MVC framework
Author-email: Frédérick NEY <frederick.ney@gmail.com>
License:                     GNU GENERAL PUBLIC LICENSE
Project-URL: Homepage, https://github.com/frederickney/flask-framework
Project-URL: Documentation, https://github.com/frederickney/flask-framework/blob/master/readme.md
Project-URL: Repository, https://github.com/frederickney/flask-framework
Project-URL: Issues, https://github.com/frederickney/flask-framework/issues
Project-URL: source, https://github.com/frederickney/flask-framework
Classifier: Environment :: Web Environment
Classifier: Intended Audience :: Developers
Classifier: Operating System :: OS Independent
Classifier: Framework :: Flask
Classifier: Topic :: Software Development :: Libraries :: Python Modules
Classifier: Programming Language :: Python :: 3.7
Classifier: Programming Language :: Python :: 3.8
Classifier: Programming Language :: Python :: 3.9
Classifier: Programming Language :: Python :: 3.10
Classifier: Programming Language :: Python :: 3.11
Classifier: Programming Language :: Python :: 3.12
Classifier: Programming Language :: Python :: 3.13
Requires-Python: >=3.7
License-File: LICENSE
Requires-Dist: certifi
Requires-Dist: Jinja2
Requires-Dist: requests
Requires-Dist: urllib3
Requires-Dist: Werkzeug
Requires-Dist: gunicorn
Requires-Dist: pyyaml
Requires-Dist: pyopenssl
Requires-Dist: WTForms
Requires-Dist: SQLAlchemy
Requires-Dist: redis
Requires-Dist: tornado
Requires-Dist: python-ldap
Requires-Dist: activedirectory
Requires-Dist: email-validator
Requires-Dist: Flask
Requires-Dist: Flask-GeoIP
Requires-Dist: Flask-LoginManager
Requires-Dist: flask-monitor
Requires-Dist: Flask-Profile
Requires-Dist: Flask-Builder
Requires-Dist: Flask-Auth
Requires-Dist: Flask-APScheduler
Requires-Dist: flask-sqlalchemy
Requires-Dist: Flask-Sessions
Requires-Dist: Flask-Login
Requires-Dist: flask-login-saml
Requires-Dist: flask-login-oidc
Requires-Dist: Flask-SocketIO
Requires-Dist: Flask-WTF
Requires-Dist: Flask-Session
Requires-Dist: Flask-Script
Requires-Dist: Flask-Migrate
Requires-Dist: importlib-metadata; python_version > "3.7"
Dynamic: license-file
